lanzou/__init__.py
lanzou/browser_cookie3.py
lanzou/debug.py
lanzou/login_assister.py
lanzou/api/__init__.py
lanzou/api/core.py
lanzou/api/extra.py
lanzou/api/models.py
lanzou/api/parser.py
lanzou/api/types.py
lanzou/api/utils.py
lanzou/gui/__init__.py
lanzou/gui/config.py
lanzou/gui/gui.py
lanzou/gui/models.py
lanzou/gui/others.py
lanzou/gui/qss.py
lanzou/gui/todo.md
lanzou/gui/ui.py
lanzou/gui/dialogs/__init__.py
lanzou/gui/dialogs/about.py
lanzou/gui/dialogs/captcha.py
lanzou/gui/dialogs/delete.py
lanzou/gui/dialogs/info.py
lanzou/gui/dialogs/login.py
lanzou/gui/dialogs/merge_file.py
lanzou/gui/dialogs/move.py
lanzou/gui/dialogs/rec_folder.py
lanzou/gui/dialogs/rename.py
lanzou/gui/dialogs/setpwd.py
lanzou/gui/dialogs/setting.py
lanzou/gui/dialogs/upload.py
lanzou/gui/workers/__init__.py
lanzou/gui/workers/desc.py
lanzou/gui/workers/down.py
lanzou/gui/workers/folders.py
lanzou/gui/workers/login.py
lanzou/gui/workers/manager.py
lanzou/gui/workers/more.py
lanzou/gui/workers/pwd.py
lanzou/gui/workers/recovery.py
lanzou/gui/workers/refresh.py
lanzou/gui/workers/rename.py
lanzou/gui/workers/rm.py
lanzou/gui/workers/share.py
lanzou/gui/workers/update.py
lanzou/gui/workers/upload.py
funlanzou-0.1.8.dist-info/METADATA
funlanzou-0.1.8.dist-info/WHEEL
funlanzou-0.1.8.dist-info/top_level.txt
funlanzou-0.1.8.dist-info/RECORD
