Metadata-Version: 2.1
Name: funlanzou
Version: 0.1.8
Summary: funlanzou
Home-page: https://github.com/farfarfun/funlanzou
Author: bingtao
Author-email: 1007530194@qq.com
